commot/__init__.py
commot/_optimal_transport/__init__.py
commot/_optimal_transport/_cot.py
commot/_optimal_transport/_unot.py
commot/_optimal_transport/_usot.py
commot/_utils/__init__.py
commot/_utils/_binarization.py
commot/_utils/_clustering.py
commot/_utils/_plotting.py
commot/_utils/_similarity.py
commot/plotting/__init__.py
commot/plotting/_plotting.py
commot/preprocessing/__init__.py
commot/preprocessing/_infer_spatial.py
commot/preprocessing/_ligand_receptor_database.py
commot/preprocessing/_data/LRdatabase/CellChat/CellChatDB.ligrec.human.csv
commot/preprocessing/_data/LRdatabase/CellChat/CellChatDB.ligrec.mouse.csv
commot/preprocessing/_data/LRdatabase/CellChat/CellChatDB.ligrec.zebrafish.csv
commot/preprocessing/_data/LRdatabase/CellPhoneDB_v4.0/CellPhoneDBv4.0.human.csv
commot/preprocessing/_data/LRdatabase/CellPhoneDB_v4.0/CellPhoneDBv4.0.mouse.csv
commot/tools/__init__.py
commot/tools/_downstream_analysis.py
commot/tools/_spatial_communication.py
commot-0.0.3.dist-info/LICENSE.md
commot-0.0.3.dist-info/METADATA
commot-0.0.3.dist-info/WHEEL
commot-0.0.3.dist-info/top_level.txt
commot-0.0.3.dist-info/RECORD
