Metadata-Version: 2.1
Name: commot
Version: 0.0.3
Summary: Cell-cell communications inference for spatial transcriptomics data via optimal transport.
Home-page: UNKNOWN
License: MIT License
Keywords: cell-cell communicaiton,spatial transcriptomics,optimal transport
Platform: UNKNOWN
Classifier: Programming Language :: Python :: 3.7
Classifier: Programming Language :: Python :: 3.8
Classifier: Programming Language :: Python :: 3.9
Classifier: License :: OSI Approved :: MIT License
Classifier: Operating System :: POSIX :: Linux
Classifier: Operating System :: MacOS
Classifier: Topic :: Scientific/Engineering
Classifier: Topic :: Scientific/Engineering :: Bio-Informatics
Requires-Python: >=3.7
License-File: LICENSE.md
Requires-Dist: anndata (>=0.7.6)
Requires-Dist: karateclub (>=1.2.2)
Requires-Dist: leidenalg (>=0.9.0)
Requires-Dist: networkx (>=2.5.1)
Requires-Dist: numpy (>=1.19.5)
Requires-Dist: pandas (>=1.3.5)
Requires-Dist: plotly (>=5.3.1)
Requires-Dist: pot (>=0.8.0)
Requires-Dist: pysal (>=2.6.0)
Requires-Dist: python-igraph (>=0.9.9)
Requires-Dist: python-louvain (>=0.15)
Requires-Dist: scanpy (>=1.8.2)
Requires-Dist: scikit-learn (>=1.0.2)
Requires-Dist: importlib-metadata
Provides-Extra: docs
Requires-Dist: sphinx (==5.3.0) ; extra == 'docs'
Requires-Dist: sphinx-autodoc-typehints (==1.18.1) ; extra == 'docs'
Requires-Dist: sphinx-rtd-theme (==1.0.0) ; extra == 'docs'
Requires-Dist: sphinx-rtd-size (==0.2.0) ; extra == 'docs'
Requires-Dist: sphinxcontrib-applehelp (==1.0.2) ; extra == 'docs'
Requires-Dist: sphinxcontrib-devhelp (==1.0.2) ; extra == 'docs'
Requires-Dist: sphinxcontrib-htmlhelp (==2.0.0) ; extra == 'docs'
Requires-Dist: sphinxcontrib-jsmath (==1.0.1) ; extra == 'docs'
Requires-Dist: sphinxcontrib-qthelp (==1.0.3) ; extra == 'docs'
Requires-Dist: sphinxcontrib-serializinghtml (==1.1.5) ; extra == 'docs'
Requires-Dist: sphinx-mdinclude (==0.5.3) ; extra == 'docs'
Requires-Dist: nbsphinx (==0.8.9) ; extra == 'docs'
Requires-Dist: ipykernel (==6.16.0) ; extra == 'docs'
Requires-Dist: sphinx-gallery (==0.11.1) ; extra == 'docs'
Provides-Extra: tradeseq
Requires-Dist: anndata2ri (==1.0.6) ; extra == 'tradeseq'
Requires-Dist: rpy2 (==3.4.2) ; extra == 'tradeseq'
